CHANGELOG.md
CLA.md
CONTRIBUTING.md
MANIFEST.in
README.md
requirements.txt
setup.py
MailManagerPythonInterface.egg-info/PKG-INFO
MailManagerPythonInterface.egg-info/SOURCES.txt
MailManagerPythonInterface.egg-info/dependency_links.txt
MailManagerPythonInterface.egg-info/entry_points.txt
MailManagerPythonInterface.egg-info/requires.txt
MailManagerPythonInterface.egg-info/top_level.txt
docs/README.md
mailmanager/__init__.py
mailmanager/sample.py
mailmanager/test/__init__.py
mailmanager/test/test_mailmanager.py