Metadata-Version: 1.1
Name: MailManagerPythonInterface
Version: 0.1.0
Summary: Mail Manager Python Interface is a Python 3 package template.
Home-page: https://github.com/KyleChamberlin/mail-manager-python-interface
Author: Kyle Chamberlin
Author-email: KyleChamberlin@project20million.org
License: MIT
Platform: UNKNOWN
Classifier: Development Status :: 1 - Planning
Classifier: Natural Language :: English
Classifier: Operating System :: OS Independent
Classifier: Programming Language :: Python :: 3.4
